{"config":{"output_file":null,"full_docs":false,"pub_only":false,"reachable_only":false,"distro_crate":false,"signatures":false,"borrow_data":false},"version":"0.19.1","compilation":{"directory":"c:\\Users\\Takuto\\Documents\\GitHub\\Rust-Book-Hand\\ch2\\tukimei","program":"C:\\Users\\Takuto\\.rustup\\toolchains\\stable-x86_64-pc-windows-msvc\\bin\\rls.exe","arguments":[],"output":"c:\\Users\\Takuto\\Documents\\GitHub\\Rust-Book-Hand\\ch2\\tukimei\\target\\rls\\debug\\deps\\libtukimei-b4e2db2dbcef3cd1.rmeta"},"prelude":{"crate_id":{"name":"tukimei","disambiguator":[1547863182024797731,0]},"crate_root":"src","external_crates":[{"file_name":"c:\\Users\\Takuto\\Documents\\GitHub\\Rust-Book-Hand\\ch2\\tukimei\\src\\main.rs","num":1,"id":{"name":"std","disambiguator":[2135196546772561304,0]}},{"file_name":"c:\\Users\\Takuto\\Documents\\GitHub\\Rust-Book-Hand\\ch2\\tukimei\\src\\main.rs","num":2,"id":{"name":"core","disambiguator":[10100063161427464349,0]}},{"file_name":"c:\\Users\\Takuto\\Documents\\GitHub\\Rust-Book-Hand\\ch2\\tukimei\\src\\main.rs","num":3,"id":{"name":"compiler_builtins","disambiguator":[18166920060419810902,0]}},{"file_name":"c:\\Users\\Takuto\\Documents\\GitHub\\Rust-Book-Hand\\ch2\\tukimei\\src\\main.rs","num":4,"id":{"name":"rustc_std_workspace_core","disambiguator":[8277429635966420526,0]}},{"file_name":"c:\\Users\\Takuto\\Documents\\GitHub\\Rust-Book-Hand\\ch2\\tukimei\\src\\main.rs","num":5,"id":{"name":"alloc","disambiguator":[1216845600797868778,0]}},{"file_name":"c:\\Users\\Takuto\\Documents\\GitHub\\Rust-Book-Hand\\ch2\\tukimei\\src\\main.rs","num":6,"id":{"name":"libc","disambiguator":[4668287356885333314,0]}},{"file_name":"c:\\Users\\Takuto\\Documents\\GitHub\\Rust-Book-Hand\\ch2\\tukimei\\src\\main.rs","num":7,"id":{"name":"unwind","disambiguator":[8817118394831127109,0]}},{"file_name":"c:\\Users\\Takuto\\Documents\\GitHub\\Rust-Book-Hand\\ch2\\tukimei\\src\\main.rs","num":8,"id":{"name":"cfg_if","disambiguator":[8504866355990175305,0]}},{"file_name":"c:\\Users\\Takuto\\Documents\\GitHub\\Rust-Book-Hand\\ch2\\tukimei\\src\\main.rs","num":9,"id":{"name":"hashbrown","disambiguator":[13162136604145443950,0]}},{"file_name":"c:\\Users\\Takuto\\Documents\\GitHub\\Rust-Book-Hand\\ch2\\tukimei\\src\\main.rs","num":10,"id":{"name":"rustc_std_workspace_alloc","disambiguator":[12752153024841339346,0]}},{"file_name":"c:\\Users\\Takuto\\Documents\\GitHub\\Rust-Book-Hand\\ch2\\tukimei\\src\\main.rs","num":11,"id":{"name":"rustc_demangle","disambiguator":[14912306932249625247,0]}},{"file_name":"c:\\Users\\Takuto\\Documents\\GitHub\\Rust-Book-Hand\\ch2\\tukimei\\src\\main.rs","num":12,"id":{"name":"std_detect","disambiguator":[13614144605518827024,0]}},{"file_name":"c:\\Users\\Takuto\\Documents\\GitHub\\Rust-Book-Hand\\ch2\\tukimei\\src\\main.rs","num":13,"id":{"name":"panic_unwind","disambiguator":[12294374008152043540,0]}}],"span":{"file_name":"src\\main.rs","byte_start":0,"byte_end":609,"line_start":1,"line_end":27,"column_start":1,"column_end":2}},"imports":[{"kind":"Use","ref_id":{"krate":1,"index":1089},"span":{"file_name":"src\\main.rs","byte_start":22,"byte_end":29,"line_start":1,"line_end":1,"column_start":23,"column_end":30},"alias_span":null,"name":"HashMap","value":"","parent":{"krate":0,"index":0}}],"defs":[{"kind":"Mod","id":{"krate":0,"index":0},"span":{"file_name":"src\\main.rs","byte_start":0,"byte_end":609,"line_start":1,"line_end":27,"column_start":1,"column_end":2},"name":"","qualname":"::","value":"src\\main.rs","parent":null,"children":[{"krate":0,"index":1},{"krate":0,"index":2},{"krate":0,"index":3},{"krate":0,"index":6}],"decl_id":null,"docs":"","sig":null,"attributes":[]},{"kind":"Function","id":{"krate":0,"index":6},"span":{"file_name":"src\\main.rs","byte_start":35,"byte_end":39,"line_start":3,"line_end":3,"column_start":4,"column_end":8},"name":"main","qualname":"::main","value":"fn main()","parent":null,"children":[],"decl_id":null,"docs":"","sig":null,"attributes":[]},{"kind":"Local","id":{"krate":0,"index":134217734},"span":{"file_name":"src\\main.rs","byte_start":52,"byte_end":56,"line_start":4,"line_end":4,"column_start":9,"column_end":13},"name":"tuki","qualname":"tuki$HirId { owner: DefId(0:6 ~ tukimei[157b]::main), local_id: 16 }","value":"[&str; 12]","parent":null,"children":[],"decl_id":null,"docs":"","sig":null,"attributes":[]},{"kind":"Local","id":{"krate":0,"index":67108870},"span":{"file_name":"src\\main.rs","byte_start":303,"byte_end":311,"line_start":19,"line_end":19,"column_start":13,"column_end":21},"name":"tuki_map","qualname":"tuki_map$HirId { owner: DefId(0:6 ~ tukimei[157b]::main), local_id: 32 }","value":"std::collections::HashMap<&str, usize>","parent":null,"children":[],"decl_id":null,"docs":"","sig":null,"attributes":[]},{"kind":"Local","id":{"krate":0,"index":3825205254},"span":{"file_name":"src\\main.rs","byte_start":361,"byte_end":362,"line_start":20,"line_end":20,"column_start":10,"column_end":11},"name":"i","qualname":"i$HirId { owner: DefId(0:6 ~ tukimei[157b]::main), local_id: 39 }","value":"usize","parent":null,"children":[],"decl_id":null,"docs":"","sig":null,"attributes":[]},{"kind":"Local","id":{"krate":0,"index":335544326},"span":{"file_name":"src\\main.rs","byte_start":364,"byte_end":365,"line_start":20,"line_end":20,"column_start":13,"column_end":14},"name":"v","qualname":"v$HirId { owner: DefId(0:6 ~ tukimei[157b]::main), local_id: 40 }","value":"&&str","parent":null,"children":[],"decl_id":null,"docs":"","sig":null,"attributes":[]}],"impls":[],"refs":[{"kind":"Mod","span":{"file_name":"src\\main.rs","byte_start":4,"byte_end":7,"line_start":1,"line_end":1,"column_start":5,"column_end":8},"ref_id":{"krate":1,"index":0}},{"kind":"Mod","span":{"file_name":"src\\main.rs","byte_start":9,"byte_end":20,"line_start":1,"line_end":1,"column_start":10,"column_end":21},"ref_id":{"krate":1,"index":988}},{"kind":"Type","span":{"file_name":"src\\main.rs","byte_start":313,"byte_end":320,"line_start":19,"line_end":19,"column_start":23,"column_end":30},"ref_id":{"krate":1,"index":1089}},{"kind":"Function","span":{"file_name":"src\\main.rs","byte_start":345,"byte_end":348,"line_start":19,"line_end":19,"column_start":55,"column_end":58},"ref_id":{"krate":1,"index":1097}},{"kind":"Type","span":{"file_name":"src\\main.rs","byte_start":336,"byte_end":343,"line_start":19,"line_end":19,"column_start":46,"column_end":53},"ref_id":{"krate":1,"index":1089}},{"kind":"Function","span":{"file_name":"src\\main.rs","byte_start":382,"byte_end":391,"line_start":20,"line_end":20,"column_start":31,"column_end":40},"ref_id":{"krate":2,"index":7863}},{"kind":"Function","span":{"file_name":"src\\main.rs","byte_start":375,"byte_end":379,"line_start":20,"line_end":20,"column_start":24,"column_end":28},"ref_id":{"krate":2,"index":11477}},{"kind":"Variable","span":{"file_name":"src\\main.rs","byte_start":370,"byte_end":374,"line_start":20,"line_end":20,"column_start":19,"column_end":23},"ref_id":{"krate":0,"index":134217734}},{"kind":"Function","span":{"file_name":"src\\main.rs","byte_start":413,"byte_end":419,"line_start":21,"line_end":21,"column_start":18,"column_end":24},"ref_id":{"krate":1,"index":1139}},{"kind":"Variable","span":{"file_name":"src\\main.rs","byte_start":404,"byte_end":412,"line_start":21,"line_end":21,"column_start":9,"column_end":17},"ref_id":{"krate":0,"index":67108870}},{"kind":"Variable","span":{"file_name":"src\\main.rs","byte_start":420,"byte_end":421,"line_start":21,"line_end":21,"column_start":25,"column_end":26},"ref_id":{"krate":0,"index":335544326}},{"kind":"Variable","span":{"file_name":"src\\main.rs","byte_start":423,"byte_end":424,"line_start":21,"line_end":21,"column_start":28,"column_end":29},"ref_id":{"krate":0,"index":3825205254}},{"kind":"Variable","span":{"file_name":"src\\main.rs","byte_start":472,"byte_end":480,"line_start":24,"line_end":24,"column_start":27,"column_end":35},"ref_id":{"krate":0,"index":67108870}},{"kind":"Variable","span":{"file_name":"src\\main.rs","byte_start":530,"byte_end":538,"line_start":25,"line_end":25,"column_start":27,"column_end":35},"ref_id":{"krate":0,"index":67108870}},{"kind":"Variable","span":{"file_name":"src\\main.rs","byte_start":587,"byte_end":595,"line_start":26,"line_end":26,"column_start":28,"column_end":36},"ref_id":{"krate":0,"index":67108870}}],"macro_refs":[],"relations":[]}